Workbook

Sheet Cover
B1: สถาบันเทคโนโลยีจิตรลดา คณะเทคโนโลยีดิจิทัล
A2: ข้อสอบวิชา 310-2203 Software Development 1
A3: หัวข้อ | B3: การสอบกลางภาค
A4: ภาคต้น ปีการศึกษา 2568
A5: จำนวนข้อสอบ | B5: อัตนัย 60 ข้อ ปรนัย 5 ข้อ
A6: คะแนนเต็ม | B6: 80 คะแนน
A7: ์ผู้สอน | B7: ดร.ศรายุทธ ฉายสุริยะ
A8: รหัสนักศึกษา
A9: ชื่อนักศึกษา
A10: นามสกุลนักศึกษา
A11: วันที่สอบ | B11: 45877
A12: เงื่อนไข | B12: ทำข้อสอบโดยใช้ Excel ในเครื่องคอมพิวเตอร์ประจำตัว ห้าม นศษ. แก้ไขเปลี่ยนแปลงข้อมูลในแผ่นงาน "ข้อมูล"
B13: ห้ามใช้อินเตอร์เน็ต และโปรแกรมอื่นใดในคอมพิวเตอร์ โดยเด็ดขาด
B14: ข้อมูลในแผ่นงาน "ข้อสอบ" ใช้เป็นคำตอบในการสอบครั้งนี้
B15: หลังทำข้อสอบเสร็จแล้ว ให้ นศษ เชื่อมต่อ อินเตอร์เน็ต แล้วใช้ email ส่งแฟ้มให้ ผู้สอน sarayut.cha@cdti.ac.th โดยตั้งชื่อแฟ้มเป็น "Midterm-SWDEV1-รหัส-ชื่อนักศึกษา"
B16: หลังส่งข้อมูลแล้ว ให้ นศษ. ออกจากห้องสอบในทันที โดยนำคอมพิวเตอร์ที่ใช้ทำข้อสอบออกไปด้วย
B17: การทุจริตในการสอบถือเป็นความผิดร้ายแรง มีโทษสูงสุดให้พ้นสภาพการเป็นนักศึกษา

Sheet ข้อสอบ
A1: แต่ละข้อ ให้นักศึกษาเลือกคำตอบที่ถูกต้องมากที่สุดได้เพียงข้อเดียว
A2: ข้อ | B2: คำถาม | C2: ตอบข้อ ก | D2: คำตอบสำหรั้บข้อ ก | E2: ตอบข้อ ข | F2: คำตอบสำหรั้บข้อ ข | G2: ตอบข้อ ค | H2: คำตอบสำหรั้บข้อ ค | I2: ตอบข้อ ง | J2: คำตอบสำหรั้บข้อ ง | K2: ภาพประกอบ(ถ้ามี)
A3: 1 | B3: ใน Visual Studio 2022 เมื่อต้องการสร้างโปรเจกต์ใหม่สำหรับแอปพลิเคชัน Windows Forms โดยใช้ภาษา C# ควรเลือก แม่แบบ (เทมเพลต) ใด? | C3: FALSE | D3: ASP.NET Core Web App | E3: FALSE | F3: Console App (.NET Core) | G3: FALSE | H3: Windows Forms App (.NET Framework) | I3: FALSE | J3: Class Library (.NET Standard)
A4: =A3+1 -> 2 | B4: ใน Visual Studio 2022 การกดปุ่ม F5 ขณะพัฒนาแอปพลิเคชัน Windows Forms มีผลอย่างไร? | C4: FALSE | D4: บันทึกไฟล์ทั้งหมดโดยไม่คอมไพล์ | E4: FALSE | F4: รันโปรแกรมในโหมด Debug | G4: FALSE | H4: ปิดหน้าต่าง Design View | I4: FALSE | J4: สร้างไฟล์ .exe โดยไม่รันโปรแกรม
A5: =A4+1 -> 3 | B5: ถ้าต้องการเพิ่ม Button Control ลงในฟอร์มใน Visual Studio 2022 ควรทำอย่างไร? | C5: FALSE | D5: คลิกขวาที่ฟอร์มและเลือก "Add New Item" | E5: FALSE | F5: ลาก Button จาก Toolbox มาวางบนฟอร์ม | G5: FALSE | H5: เขียนโค้ดสร้าง Button ในไฟล์ Program.cs | I5: FALSE | J5: ดับเบิลคลิกที่ฟอร์มเพื่อสร้าง Button อัตโนมัติ
A6: =A5+1 -> 4 | B6: หลังจากเพิ่ม TextBox ชื่อ txtName และ Button ชื่อ btnSubmit ในฟอร์ม นักพัฒนาต้องการให้เมื่อคลิกปุ่ม btnSubmit โปรแกรมแสดงข้อความ "Hello, [ชื่อที่ป้อน]" ใน MessageBox ควรเขียนโค้ดอย่างไร? | C6: FALSE | D6: private void btnSubmit_Click(object sender, EventArgs e) { MessageBox.Show("Hello, " + txtName.Text); } | E6: FALSE | F6: private void btnSubmit_Click(object sender, EventArgs e) { Console.WriteLine("Hello, " + txtName.Text); } | G6: FALSE | H6: private void Form1_Load(object sender, EventArgs e) { MessageBox.Show("Hello, " + txtName.Text); } | I6: FALSE | J6: private void txtName_TextChanged(object sender, EventArgs e) { MessageBox.Show("Hello, " + txtName.Text); }
A7: =A6+1 -> 5 | B7: นักพัฒนาต้องการตรวจสอบว่าค่าในตัวแปร count ถูกอัปเดตอย่างถูกต้องขณะรันโปรแกรมในโหมด Debug วิธีใดเหมาะสมที่สุด? | C7: FALSE | D7: ใช้คำสั่ง Console.WriteLine(count) เพื่อแสดงค่าใน Output Window | E7: FALSE | F7: ใช้ Breakpoint และดูค่าใน Watch Window | G7: FALSE | H7: แก้ไขโค้ดให้แสดง MessageBox ทุกครั้งที่ค่า count เปลี่ยน | I7: FALSE | J7: รันโปรแกรมปกติและบันทึกผลลัพธ์ลงไฟล์
A8: =A7+1 -> 6 | B8: ในภาษา C# คีย์เวิร์ดใดใช้สำหรับประกาศตัวแปรที่เก็บค่าจำนวนเต็มแบบมีเครื่องหมายขนาด 32 บิต? | C8: FALSE | D8: float | E8: FALSE | F8: double | G8: FALSE | H8: int | I8: FALSE | J8: string
A9: =A8+1 -> 7 | B9: ข้อใดคือการประกาศตัวแปรและกำหนดค่าเริ่มต้นที่ถูกต้องในภาษา C#? | C9: FALSE | D9: int x = "5"; | E9: FALSE | F9: string name = 'John'; //(ใช้ single quotes) | G9: FALSE | H9: bool isActive = true; | I9: FALSE | J9: double price = 10.5f; //(ใช้ suffix f สำหรับ double)
A10: =A9+1 -> 8 | B10: จากโค้ดต่อไปนี้ ผลลัพธ์ที่ได้คืออะไร? string message = "Hello"; message += " World"; Console.WriteLine(message.Length); | C10: FALSE | D10: 5 | E10: FALSE | F10: 6 | G10: FALSE | H10: 11 | I10: FALSE | J10: เกิดข้อผิดพลาด
A11: =A10+1 -> 9 | B11: ข้อใดคือวิธีที่ดีที่สุดในการตรวจสอบว่าสตริง input เป็นค่าว่างหรือไม่? | C11: FALSE | D11: if (input == "") | E11: FALSE | F11: if (input == string.Empty) | G11: FALSE | H11: if (string.IsNullOrEmpty(input)) | I11: FALSE | J11: if (input.Length <= 0)
A12: =A11+1 -> 10 | B12: จากโค้ดต่อไปนี้ ข้อใดคือผลลัพธ์และเหตุผลที่ถูกต้อง? int a = 10; int b = 3; double result = a / b; Console.WriteLine(result); | C12: FALSE | D12: 3.333 — เพราะ a / b คำนวณเป็นทศนิยมอัตโนมัติ | E12: FALSE | F12: 3 — เพราะ a และ b เป็น int จึงหารแบบจำนวนเต็ม | G12: FALSE | H12: เกิดข้อผิดพลาด — เพราะไม่สามารถแปลง int เป็น double ได้ | I12: FALSE | J12: 3.0 — เพราะ result เป็น double
A13: =A12+1 -> 11 | B13: ขั้นตอนใดใน SDLC ที่เกี่ยวข้องกับการวิเคราะห์ความต้องการของผู้ใช้และกำหนดขอบเขตของระบบ? | C13: FALSE | D13: การออกแบบระบบ (System Design) | E13: FALSE | F13: การทดสอบระบบ (Testing) | G13: FALSE | H13: การเก็บความต้องการ (Requirements Gathering) | I13: FALSE | J13: การบำรุงรักษา (Maintenance)
A14: =A13+1 -> 12 | B14: หากองค์กรอยู่ใน CMMI Level 3 (Defined) ข้อใดสะท้อนลักษณะการทำงานได้ถูกต้องที่สุด? | C14: FALSE | D14: กระบวนการพัฒนาซอฟต์แวร์ถูกกำหนดเป็นมาตรฐานและปรับใช้ทั่วทั้งองค์กร | E14: FALSE | F14: โครงการต่าง ๆ ทำงานแบบ Ad-hoc โดยไม่มีกระบวนการชัดเจน | G14: FALSE | H14: มีการวัดผลและปรับปรุงกระบวนการอย่างต่อเนื่อง (Quantitatively Managed) | I14: FALSE | J14: กระบวนการพัฒนาถูกปรับปรุงโดยอัตโนมัติด้วย AI
A15: =A14+1 -> 13 | B15: จากโค้ดต่อไปนี้ วิธีใดคือการจัดการหน่วยความจำที่มีประสิทธิภาพที่สุด หากต้องการสตริงที่สามารถแก้ไขได้หลายครั้ง? string data = "Initial"; // แก้ไขสตริงหลายครั้ง (เช่น ต่อข้อความหรือลบบางส่วน) | C15: FALSE | D15: ใช้ string และดำเนินการต่อด้วย += ตลอด | E15: FALSE | F15: ใช้ StringBuilder | G15: FALSE | H15: ใช้ char[] และจัดการแบบอาร์เรย์ | I15: FALSE | J15: ใช้ List<string> และ Join() ทุกครั้ง
A16: =A15+1 -> 14 | B16: สัญลักษณ์ใดใน Activity Diagram ที่ใช้แทนการตัดสินใจ (Decision) และมีเส้นทางออกได้หลายทาง? | C16: FALSE | D16: ◻️ สี่เหลี่ยม (Activity) | E16: FALSE | F16: 🔵 วงกลมทึบ (Start Node) | G16: FALSE | H16: ⭕ วงกลมเส้นบาง (End Node) | I16: FALSE | J16: 🔷 สี่เหลี่ยมข้าวหลามตัด (Diamond)
A17: =A16+1 -> 15 | B17: จากกระบวนการลงทะเบียนผู้ใช้ต่อไปนี้ ข้อใดสะท้อนการออกแบบ Activity Diagram ที่เหมาะสมที่สุด? 1.เริ่มต้น 2.กรอกแบบฟอร์ม 3.ตรวจสอบความถูกต้องของข้อมูล - หากข้อมูลถูกต้อง: บันทึกข้อมูล - หากข้อมูลไม่ถูกต้อง: แจ้งข้อผิดพลาดและกลับไปกรอกใหม่ 4.ส่งอีเมลยืนยัน 5.จบกระบวนการ | C17: FALSE | D17: ใช้ Merge Node (⚪) รวมทุกเส้นทางก่อนจบกระบวนการ | E17: FALSE | F17: ใช้ Decision Node (🔷) เฉพาะขั้นตอนตรวจสอบข้อมูล โดยไม่มี Merge Node | G17: FALSE | H17: ใช้ Parallel Fork (➖) สำหรับขั้นตอนส่งอีเมลและบันทึกข้อมูลพร้อมกัน | I17: FALSE | J17: ใช้ Final Node (⭕) 2 จุด (เมื่อบันทึกสำเร็จและเมื่อมีข้อผิดพลาด)
A18: =A17+1 -> 16 | B18: จากระบบ ATM ต่อไปนี้ ข้อใดเป็นการออกแบบ Use Case Diagram ที่เหมาะสมที่สุด? ความต้องการ: 1.ผู้ใช้ (Actor: Customer) สามารถทำธุรกรรมถอนเงินและตรวจสอบยอดเงิน 2.การถอนเงินต้องมีการตรวจสอบ PIN ก่อนเสมอ 3.เจ้าหน้าที่ธนาคาร (Actor: Bank Staff) สามารถเติมเงินในเครื่องได้ | C18: FALSE | D18: - Use Case: "Withdraw Money" และ "Check Balance" แยกกันโดยไม่มีความสัมพันธ์ - ไม่มี Use Case "Verify PIN" | E18: FALSE | F18: -Use Case: "Withdraw Money" รวมความสัมพันธ์ <<include>> กับ "Verify PIN" -Use Case: "Check Balance" รวมความสัมพันธ์ <<extend>> กับ "Verify PIN" -มี Actor "Bank Staff" ที่เกี่ยวข้องกับ Use Case "Refill Cash | G18: FALSE | H18: -Use Case: "Withdraw Money" และ "Check Balance" ใช้ความสัมพันธ์ <<extend>> กับ "Verify PIN" -ไม่มี Actor "Bank Staff" | I18: FALSE | J18: -Use Case: "Withdraw Money" และ "Check Balance" รวมเป็น Use Case เดียวกัน - มี Actor "Bank Staff" แต่ไม่มี Use Case "Refill Cash"
A19: =A18+1 -> 17 | B19: จากผลการสำรวจผู้ใช้ระบบจองห้องพัก พบว่า 70% ของผู้ใช้ไม่พอใจขั้นตอนการชำระเงินที่ซับซ้อน ข้อใดคือแนวทางการแก้ไขปัญหาที่เหมาะสมที่สุด? | C19: FALSE | D19: เพิ่มฟีเจอร์การแจ้งเตือนทางอีเมลเพื่อลดความสับสน | E19: FALSE | F19: ปรับขั้นตอนการชำระเงินให้เหลือไม่เกิน 3 ขั้นตอน และทดสอบ usability กับกลุ่มผู้ใช้อีกครั้ง | G19: FALSE | H19: ลดราคาห้องพักเพื่อชดเชยความไม่สะดวก | I19: FALSE | J19: เพิ่มคู่มือการใช้งานแบบ PDF ในเว็บไซต์
A20: =A19+1 -> 18 | B20: ตามหลัก Hungarian Notation ในการเขียนโค้ด ตัวแปรชื่อ strUserName ควรมีข้อมูลประเภทใด? | C20: FALSE | D20: ตัวเลขจำนวนเต็ม (int) | E20: FALSE | F20: สตริง (string) | G20: FALSE | H20: ค่าทางตรรกะ (bool) | I20: FALSE | J20: วันที่และเวลา (DateTime)
A21: =A20+1 -> 19 | B21: จากโค้ด C# ต่อไปนี้ ข้อใดเป็นปัญหาตามหลักมาตรฐานการเขียนโค้ดที่ดีที่สุด? public void CalculateTotal(int p1, int p2) { int x = p1 + p2; Console.WriteLine(x); } | C21: FALSE | D21: ใช้ชื่อตัวแปร p1 และ p2 ที่ไม่สื่อความหมาย | E21: FALSE | F21: ไม่มีการคืนค่า (return value) จากเมธอด | G21: FALSE | H21: ไม่มี comment อธิบายการทำงาน | I21: FALSE | J21: ใช้ตัวแปรชั่วคราว x แทนการคำนวณโดยตรงใน Console.WriteLine
A22: =A21+1 -> 20 | B22: หลักการสำคัญของ Defensive Coding คืออะไร? | C22: FALSE | D22: เขียนโค้ดให้สั้นที่สุดเท่าที่จะเป็นไปได้ | E22: FALSE | F22: คาดการณ์และป้องกันข้อผิดพลาดที่อาจเกิดขึ้นจาก input หรือสภาพแวดล้อม | G22: FALSE | H22: ใช้ algorithm ที่ซับซ้อนเพื่อเพิ่มประสิทธิภาพ | I22: FALSE | J22: ลดการใช้ comment ในโค้ดเพื่อความปลอดภัย
... A40: =A39+1 -> 38 | B40: เมธอด Substring() ใน C# ใช้ทำอะไร? | C40: FALSE | D40: แยกสตริงย่อยจากสตริงหลักตามตำแหน่งและความยาวที่กำหนด | E40: FALSE | F40: เปรียบเทียบสองสตริงว่าตรงกันหรือไม่ | G40: FALSE | H40: แปลงสตริงเป็นตัวเลข | I40: FALSE | J40: เชื่อมต่อสองสตริงเข้าด้วยกัน
A41: =A40+1 -> 39 | B41: จากโค้ดต่อไปนี้ ผลลัพธ์จะเป็นอย่างไร? string str1 = "Hello"; string str2 = "hello"; int result = string.Compare(str1, str2, StringComparison.OrdinalIgnoreCase); Console.WriteLine(result); | C41: FALSE | D41: -1 | E41: FALSE | F41: 0 | G41: FALSE | H41: 1 | I41: FALSE | J41: เกิดข้อผิดพลาด
A42: =A41+1 -> 40 | B42: การทดสอบแบบใดที่ตรวจสอบว่าระบบทำงานตามความต้องการของผู้ใช้หรือไม่? | C42: FALSE | D42: Unit Testing | E42: FALSE | F42: Integration Testing | G42: FALSE | H42: System Testing | I42: FALSE | J42: Acceptance Testing
A43: =A42+1 -> 41 | B43: คุณสมบัติใดของ DateTimePicker ที่ใช้กำหนดรูปแบบการแสดงผลวันที่? | C43: FALSE | D43: .Text | E43: FALSE | F43: .DateFormat | G43: FALSE | H43: .Format | I43: FALSE | J43: .Value
A44: =A43+1 -> 42 | B44: จากฟอร์มที่มี NumericUpDown (ชื่อ numQuantity) และ TextBox (ชื่อ txtTotal) ต้องการคำนวณ Total = Quantity * 100 ทุกครั้งที่ค่ามีการเปลี่ยนแปลง ควรใช้เหตุการณ์ (Event) ใด? | C44: FALSE | D44: numQuantity_TextChanged | E44: FALSE | F44: numQuantity_ValueChanged | G44: FALSE | H44: txtTotal_KeyPress | I44: FALSE | J44: numQuantity_Click
A45: =A44+1 -> 43 | B45: ต้องการตรวจสอบว่า TextBox (ชื่อ txtAge) มีค่าที่กรอกเป็นตัวเลขเท่านั้น ควรใช้โค้ดใดในเหตุการณ์ txtAge_KeyPress? | C45: FALSE | D45: private void txtAge_KeyPress(object sender, KeyPressEventArgs e) { if (!char.IsDigit(e.KeyChar)) { e.Handled = true; // ไม่ให้ป้อนอักขระที่ไม่ใช่ตัวเลข } } | E45: FALSE | F45: private void txtAge_KeyPress(object sender, KeyPressEventArgs e) { if (char.IsLetter(e.KeyChar)) { e.Handled = false; } } | G45: FALSE | H45: private void txtAge_KeyPress(object sender, KeyPressEventArgs e) { MessageBox.Show("กรุณากรอกตัวเลข"); } | I45: FALSE | J45: private void txtAge_KeyPress(object sender, KeyPressEventArgs e) { txtAge.Text = ""; }
A46: =A45+1 -> 44 | B46: หากต้องการให้ข้อความในแท็ก <p> มีสีแดง ควรใช้รูปแบบใด? | C46: FALSE | D46: <p style="color:red;">ข้อความ</p> | E46: FALSE | F46: <p color="red">ข้อความ</p> | G46: FALSE | H46: <p color="red">ข้อความ</p> | I46: FALSE | J46: <p color="red">ข้อความ</p>
A47: =A46+1 -> 45 | B47: ใน Visual Studio คีย์เวิร์ดใดใช้สำหรับสร้าง XML Comments ที่แสดงคำอธิบายเมธอดแบบมาตรฐาน? | C47: FALSE | D47: // | E47: FALSE | F47: /* */ | G47: FALSE | H47: /// | I47: FALSE | J47: '''
A48: =A47+1 -> 46 | B48: จากโค้ดต่อไปนี้ ต้องการเพิ่ม XML Comments สำหรับพารามิเตอร์และค่าที่คืนกลับ ควรเขียนอย่างไร? | C48: FALSE | D48: public int Calculate(int a, int b) { return a + b; } | E48: FALSE | F48: /// Adds two numbers public int Calculate(int a, int b) { return a + b; } | G48: FALSE | H48: /// <summary> /// บวกเลขสองตัว /// </summary> /// <param name="a">ตัวเลขแรก</param> /// <param name="b">ตัวเลขที่สอง</param> /// <returns>ผลรวมของ a และ b</returns> public int Calculate(int a, int b) { return a + b; } | I48: FALSE | J48: // Calculate a + b public int Calculate(int a, int b) { return a + b; }
A49: =A48+1 -> 47 | B49: ข้อใดคือองค์ประกอบที่จำเป็นใน Use Case Diagram สำหรับระบุความต้องการซอฟต์แวร์? | C49: FALSE | D49: Actor, Use Case, ความสัมพันธ์ (Relationship) | E49: FALSE | F49: Class, Object, Method | G49: FALSE | H49: Activity Node, Decision Node | I49: FALSE | J49: Table, Column, Primary Key
A50: =A49+1 -> 48 | B50: จากระบบห้องสมุดโรงเรียนที่มี Actor คือ "นักเรียน", "ครู", และ "บรรณารักษ์" ข้อใดแสดง Use Case Diagram ที่สมบูรณ์ที่สุด? | C50: FALSE | D50: [นักเรียน] ──> [ยืมหนังสือ] [ครู] ──> [จองหนังสือล่วงหน้า] | E50: FALSE | F50: [นักเรียน] ──> [ยืมหนังสือ] (Include) ──> [ตรวจสอบสถานะหนังสือ] [ครู] ──> [ขอหนังสืออ้างอิง] [บรรณารักษ์] ──> [เพิ่มหนังสือใหม่] | G50: FALSE | H50: [นักเรียน] ──> [ยืมหนังสือ] (Extend) ──> [ชำระค่าปรับ] [ครู] ──> [อัปเดตฐานข้อมูล] | I50: FALSE | J50: [นักเรียน] ──> [อ่านหนังสือในห้องสมุด] [บรรณารักษ์] ──> [ยืมหนังสือ]
A51: =A50+1 -> 49 | B51: จากระบบ Facebook ที่มี Actor คือ "ผู้ใช้ทั่วไป", "ผู้ดูแลระบบ", และ "นักโฆษณา" ข้อใดแสดง Use Case Diagram ที่สมบูรณ์ที่สุด? | C51: FALSE | D51: [ผู้ใช้ทั่วไป] ──> [โพสต์สถานะ] [นักโฆษณา] ──> [ดูสถิติโฆษณา] | E51: FALSE | F51: [ผู้ใช้ทั่วไป] ──> [โพสต์สถานะ] (Include) ──> [อัปโหลดรูปภาพ] [ผู้ใช้ทั่วไป] ──> [ส่งข้อความส่วนตัว] [ผู้ดูแลระบบ] ──> [ระงับบัญชีผู้ใช้] [นักโฆษณา] ──> [สร้างโฆษณา] | G51: FALSE | H51: [ผู้ใช้ทั่วไป] ──> [โพสต์สถานะ] (Extend) ──> [แท็กเพื่อน] [ผู้ดูแลระบบ] ──> [โพสต์สถานะ] | I51: FALSE | J51: [ผู้ใช้ทั่วไป] ──> [ดูสถิติโฆษณา] [นักโฆษณา] ──> [ส่งข้อความส่วนตัว]
A52: =A51+1 -> 50 | B52: หลักการใดที่สำคัญที่สุดในการเก็บรวบรวมความต้องการจากผู้ใช้เพื่อให้เป็นไปตามจริยธรรม? | C52: FALSE | D52: การเก็บข้อมูลส่วนตัวผู้ใช้โดยไม่แจ้งให้ทราบ | E52: FALSE | F52: การขอความยินยอมและอธิบายวัตถุประสงค์ก่อนเก็บข้อมูล | G52: FALSE | H52: การใช้ข้อมูลที่เก็บมาเพื่อประโยชน์ส่วนตัว | I52: FALSE | J52: การบังคับให้ผู้ใช้ให้ข้อมูลทั้งหมด
A53: =A52+1 -> 51 | B53: หากลูกค้าระบุความต้องการให้ระบบสามารถดักจับข้อมูลการสนทนาของผู้ใช้โดยไม่แจ้งให้ทราบ วิศวกรซอฟต์แวร์ควรทำอย่างไร? | C53: FALSE | D53: พัฒนาตามที่ลูกค้าต้องการโดยไม่มีข้อโต้แย้ง | E53: FALSE | F53: ปฏิเสธและอธิบายผลกระทบด้านจริยธรรม พร้อมเสนอทางเลือกอื่น | G53: FALSE | H53: พัฒนาระบบแต่เพิ่มฟังก์ชันลับๆ เพื่อดักจับข้อมูลเพิ่มเติม | I53: FALSE | J53: แจ้งให้ผู้ใช้ทราบแต่ยังพัฒนาตามที่ลูกค้าต้องการ
... A62: =A61+1 -> 60 | B62: Process Area ใดใน CMMI ที่เกี่ยวข้องกับการใช้ Usecase model? | C62: FALSE | D62: Requirements Management (REQM) | E62: FALSE | F62: Risk Management (RSKM) | G62: FALSE | H62: Project Planning (PP) | I62: FALSE | J62: Configuration Management (CM)

Sheet ข้อมูล
A4: ข้อ | B4: คำถาม | D4: 6510301028 | E4: 6510301047 | F4: 6710301001 | G4: 6710301002 | H4: 6710301003 | I4: 6710301004 | J4: 6710301005 | K4: 6710301006 | L4: 6710301007 | M4: 6710301008 | N4: 6710301009 | O4: 6710301010 | P4: 6710301011 | Q4: 6710301012 | R4: 6710301017 | S4: 6710301018 | T4: 6710301019 | U4: 6710301020 | V4: 6710301021 | W4: 6710301022 | X4: 6710301023 | Y4: 6710301024 | Z4: 6710301025 | AA4: 6710301027 | AB4: 6710301028 | AC4: 6710301029 | AD4: 6710301030 | AE4: 6710301031 | AF4: 6710301032 | AG4: 6710301033 | AH4: 6710301034 | AI4: 6710301035 | AJ4: 6710301036 | AK4: 6710301037 | AL4: 6710301041 | AM4: 6710301042 | AN4: 6710301043 | AO4: 6710301045 | AP4: 6710301047 | AQ4: 6710301048 | AR4: 6710301049 | AS4: 6710301051 | AT4: 6710301054 | AU4: 6720301001 | AV4: 6720301002 | AW4: 6720301003 | AX4: 6720301004
A5: 1 | B5: =ข้อสอบ!B3 -> ใน Visual Studio 2022 เมื่อต้องการสร้างโปรเจกต์ใหม่สำหรับแอปพลิเคชัน Windows Forms โดยใช้ภาษา C# ควรเลือก แม่แบบ (เทมเพลต) ใด? | D5: 1 | E5: 1 | F5: 1 | G5: 1 | H5: 1 | I5: 1 | J5: 1 | K5: 1 | L5: 1 | M5: 1 | N5: 1 | O5: 1 | P5: 1 | Q5: 1 | R5: 1 | S5: 1 | T5: 1 | U5: 1 | V5: 1 | W5: 1 | X5: 1 | Y5: 1 | Z5: 1 | AA5: 1 | AB5: 1 | AC5: 1 | AD5: 1 | AE5: 1 | AF5: 1 | AG5: 1 | AH5: 1 | AI5: 1 | AJ5: 1 | AL5: 1 | AM5: 1 | AN5: 1 | AO5: 1 | AP5: 1 | AQ5: 1 | AR5: 1 | AS5: 0 | AT5: 1 | AU5: 1 | AV5: 1 | AW5: 1 | AX5: 1
A6: =A5+1 -> 2 | B6: =ข้อสอบ!B4 -> ใน Visual Studio 2022 การกดปุ่ม F5 ขณะพัฒนาแอปพลิเคชัน Windows Forms มีผลอย่างไร? | D6: 1 | E6: 1 | F6: 1 | G6: 1 | H6: 1 | I6: 1 | J6: 1 | K6: 1 | L6: 1 | M6: 1 | N6: 1 | O6: 1 | P6: 1 | Q6: 1 | R6: 1 | S6: 1 | T6: 0 | U6: 1 | V6: 1 | W6: 1 | X6: 1 | Y6: 1 | Z6: 1 | AA6: 1 | AB6: 1 | AC6: 1 | AD6: 1 | AE6: 1 | AF6: 1 | AG6: 1 | AH6: 1 | AI6: 1 | AJ6: 0 | AL6: 1 | AM6: 0 | AN6: 1 | AO6: 1 | AP6: 1 | AQ6: 1 | AR6: 1 | AS6: 0 | AT6: 1 | AU6: 1 | AV6: 1 | AW6: 1 | AX6: 1
A7: =A6+1 -> 3 | B7: =ข้อสอบ!B5 -> ถ้าต้องการเพิ่ม Button Control ลงในฟอร์มใน Visual Studio 2022 ควรทำอย่างไร? | D7: 1 | E7: 1 | F7: 1 | G7: 1 | H7: 1 | I7: 1 | J7: 1 | K7: 1 | L7: 1 | M7: 1 | N7: 1 | O7: 1 | P7: 1 | Q7: 1 | R7: 1 | S7: 1 | T7: 0 | U7: 1 | V7: 1 | W7: 1 | X7: 1 | Y7: 1 | Z7: 0 | AA7: 1 | AB7: 1 | AC7: 0 | AD7: 1 | AE7: 1 | AF7: 1 | AG7: 1 | AH7: 1 | AI7: 1 | AJ7: 1 | AL7: 1 | AM7: 1 | AN7: 1 | AO7: 1 | AP7: 1 | AQ7: 1 | AR7: 1 | AS7: 0 | AT7: 0 | AU7: 1 | AV7: 1 | AW7: 1 | AX7: 1
A8: =A7+1 -> 4 | B8: =ข้อสอบ!B6 -> หลังจากเพิ่ม TextBox ชื่อ txtName และ Button ชื่อ btnSubmit ในฟอร์ม นักพัฒนาต้องการให้เมื่อคลิกปุ่ม btnSubmit โปรแกรมแสดงข้อความ "Hello, [ชื่อที่ป้อน]" ใน MessageBox ควรเขียนโค้ดอย่างไร? | D8: 1 | E8: 1 | F8: 1 | G8: 1 | H8: 1 | I8: 0 | J8: 1 | K8: 1 | L8: 1 | M8: 1 | N8: 1 | O8: 1 | P8: 1 | Q8: 1 | R8: 1 | S8: 1 | T8: 1 | U8: 0 | V8: 0 | W8: 1 | X8: 1 | Y8: 1 | Z8: 1 | AA8: 1 | AB8: 1 | AC8: 0 | AD8: 0 | AE8: 1 | AF8: 1 | AG8: 1 | AH8: 1 | AI8: 1 | AJ8: 1 | AL8: 0 | AM8: 1 | AN8: 1 | AO8: 1 | AP8: 1 | AQ8: 1 | AR8: 1 | AS8: 0 | AT8: 1 | AU8: 1 | AV8: 1 | AW8: 1 | AX8: 1
A9: =A8+1 -> 5 | B9: =ข้อสอบ!B7 -> นักพัฒนาต้องการตรวจสอบว่าค่าในตัวแปร count ถูกอัปเดตอย่างถูกต้องขณะรันโปรแกรมในโหมด Debug วิธีใดเหมาะสมที่สุด? | D9: 1 | E9: 1 | F9: 1 | G9: 0 | H9: 0 | I9: 0 | J9: 1 | K9: 1 | L9: 1 | M9: 1 | N9: 1 | O9: 1 | P9: 1 | Q9: 0 | R9: 0 | S9: 0 | T9: 0 | U9: 0 | V9: 0 | W9: 1 | X9: 1 | Y9: 0 | Z9: 0 | AA9: 1 | AB9: 1 | AC9: 0 | AD9: 1 | AE9: 0 | AF9: 1 | AG9: 0 | AH9: 0 | AI9: 1 | AJ9: 0 | AL9: 1 | AM9: 0 | AN9: 1 | AO9: 0 | AP9: 1 | AQ9: 1 | AR9: 0 | AS9: 0 | AT9: 0 | AU9: 0 | AV9: 0 | AW9: 1 | AX9: 1
A10: =A9+1 -> 6 | B10: =ข้อสอบ!B8 -> ในภาษา C# คีย์เวิร์ดใดใช้สำหรับประกาศตัวแปรที่เก็บค่าจำนวนเต็มแบบมีเครื่องหมายขนาด 32 บิต? | D10: 1 | E10: 1 | F10: 1 | G10: 1 | H10: 0 | I10: 1 | J10: 1 | K10: 1 | L10: 1 | M10: 1 | N10: 1 | O10: 1 | P10: 1 | Q10: 1 | R10: 1 | S10: 0 | T10: 1 | U10: 1 | V10: 1 | W10: 1 | X10: 1 | Y10: 0 | Z10: 0 | AA10: 1 | AB10: 1 | AC10: 1 | AD10: 1 | AE10: 0 | AF10: 1 | AG10: 1 | AH10: 1 | AI10: 1 | AJ10: 1 | AL10: 1 | AM10: 1 | AN10: 1 | AO10: 0 | AP10: 1 | AQ10: 1 | AR10: 1 | AS10: 1 | AT10: 0 | AU10: 1 | AV10: 1 | AW10: 0 | AX10: 0
A11: =A10+1 -> 7 | B11: =ข้อสอบ!B9 -> ข้อใดคือการประกาศตัวแปรและกำหนดค่าเริ่มต้นที่ถูกต้องในภาษา C#? | D11: 0 | E11: 1 | F11: 1 | G11: 0 | H11: 0 | I11: 1 | J11: 1 | K11: 1 | L11: 1 | M11: 1 | N11: 1 | O11: 1 | P11: 1 | Q11: 1 | R11: 0 | S11: 0 | T11: 1 | U11: 0 | V11: 0 | W11: 1 | X11: 1 | Y11: 0 | Z11: 0 | AA11: 0 | AB11: 0 | AC11: 0 | AD11: 0 | AE11: 0 | AF11: 1 | AG11: 0 | AH11: 0 | AI11: 1 | AJ11: 0 | AL11: 1 | AM11: 0 | AN11: 0 | AO11: 1 | AP11: 1 | AQ11: 1 | AR11: 1 | AS11: 0 | AT11: 0 | AU11: 0 | AV11: 0 | AW11: 0 | AX11: 0
A12: =A11+1 -> 8 | B12: =ข้อสอบ!B10 -> จากโค้ดต่อไปนี้ ผลลัพธ์ที่ได้คืออะไร? string message = "Hello"; message += " World"; Console.WriteLine(message.Length); | D12: 1 | E12: 1 | F12: 1 | G12: 1 | H12: 1 | I12: 1 | J12: 1 | K12: 1 | L12: 1 | M12: 1 | N12: 1 | O12: 1 | P12: 1 | Q12: 1 | R12: 0 | S12: 0 | T12: 1 | U12: 0 | V12: 0 | W12: 1 | X12: 1 | Y12: 0 | Z12: 1 | AA12: 1 | AB12: 1 | AC12: 1 | AD12: 1 | AE12: 1 | AF12: 1 | AG12: 1 | AH12: 0 | AI12: 1 | AJ12: 0 | AL12: 1 | AM12: 0 | AN12: 1 | AO12: 1 | AP12: 1 | AQ12: 1 | AR12: 0 | AS12: 0 | AT12: 0 | AU12: 1 | AV12: 0 | AW12: 0 | AX12: 0
A13: =A12+1 -> 9 | B13: =ข้อสอบ!B11 -> ข้อใดคือวิธีที่ดีที่สุดในการตรวจสอบว่าสตริง input เป็นค่าว่างหรือไม่? | D13: 0 | E13: 1 | F13: 1 | G13: 0 | H13: 1 | I13: 0 | J13: 1 | K13: 1 | L13: 1 | M13: 1 | N13: 1 | O13: 1 | P13: 1 | Q13: 0 | R13: 0 | S13: 0 | T13: 0 | U13: 0 | V13: 0 | W13: 1 | X13: 1 | Y13: 0 | Z13: 1 | AA13: 1 | AB13: 1 | AC13: 1 | AD13: 0 | AE13: 0 | AF13: 1 | AG13: 0 | AH13: 1 | AI13: 1 | AJ13: 0 | AL13: 1 | AM13: 0 | AN13: 1 | AO13: 0 | AP13: 1 | AQ13: 1 | AR13: 0 | AS13: 0 | AT13: 0 | AU13: 1 | AV13: 1 | AW13: 0 | AX13: 1
A14: =A13+1 -> 10 | B14: =ข้อสอบ!B12 -> จากโค้ดต่อไปนี้ ข้อใดคือผลลัพธ์และเหตุผลที่ถูกต้อง? int a = 10; int b = 3; double result = a / b; Console.WriteLine(result); | D14: 1 | E14: 1 | F14: 1 | G14: 0 | H14: 0 | I14: 0 | J14: 1 | K14: 0 | L14: 1 | M14: 1 | N14: 1 | O14: 1 | P14: 1 | Q14: 0 | R14: 1 | S14: 0 | T14: 1 | U14: 0 | V14: 0 | W14: 1 | X14: 1 | Y14: 0 | Z14: 0 | AA14: 1 | AB14: 1 | AC14: 0 | AD14: 0 | AE14: 0 | AF14: 1 | AG14: 0 | AH14: 0 | AI14: 1 | AJ14: 0 | AL14: 1 | AM14: 1 | AN14: 0 | AO14: 1 | AP14: 1 | AQ14: 1 | AR14: 0 | AS14: 0 | AT14: 0 | AU14: 0 | AV14: 0 | AW14: 0 | AX14: 0
A15: =A14+1 -> 11 | B15: =ข้อสอบ!B13 -> ขั้นตอนใดใน SDLC ที่เกี่ยวข้องกับการวิเคราะห์ความต้องการของผู้ใช้และกำหนดขอบเขตของระบบ? | D15: 0 | E15: 1 | F15: 1 | G15: 1 | H15: 1 | I15: 0 | J15: 1 | K15: 1 | L15: 1 | M15: 0 | N15: 1 | O15: 1 | P15: 1 | Q15: 1 | R15: 1 | S15: 1 | T15: 0 | U15: 1 | V15: 1 | W15: 1 | X15: 1 | Y15: 1 | Z15: 0 | AA15: 1 | AB15: 0 | AC15: 0 | AD15: 1 | AE15: 1 | AF15: 1 | AG15: 0 | AH15: 1 | AI15: 1 | AJ15: 0 | AL15: 1 | AM15: 0 | AN15: 1 | AO15: 1 | AP15: 1 | AQ15: 1 | AR15: 0 | AS15: 1 | AT15: 1 | AU15: 1 | AV15: 1 | AW15: 0 | AX15: 0
A16: =A15+1 -> 12 | B16: =ข้อสอบ!B14 -> หากองค์กรอยู่ใน CMMI Level 3 (Defined) ข้อใดสะท้อนลักษณะการทำงานได้ถูกต้องที่สุด? | D16: 1 | E16: 1 | F16: 1 | G16: 1 | H16: 0 | I16: 1 | J16: 1 | K16: 1 | L16: 0 | M16: 0 | N16: 1 | O16: 1 | P16: 1 | Q16: 1 | R16: 1 | S16: 1 | T16: 0 | U16: 0 | V16: 1 | W16: 1 | X16: 1 | Y16: 0 | Z16: 1 | AA16: 0 | AB16: 1 | AC16: 0 | AD16: 1 | AE16: 1 | AF16: 1 | AG16: 0 | AH16: 0 | AI16: 1 | AJ16: 1 | AL16: 1 | AM16: 1 | AN16: 1 | AO16: 1 | AP16: 1 | AQ16: 0 | AR16: 1 | AS16: 1 | AT16: 1 | AU16: 1 | AV16: 0 | AW16: 1 | AX16: 0
A17: =A16+1 -> 13 | B17: =ข้อสอบ!B15 -> จากโค้ดต่อไปนี้ วิธีใดคือการจัดการหน่วยความจำที่มีประสิทธิภาพที่สุด หากต้องการสตริงที่สามารถแก้ไขได้หลายครั้ง? string data = "Initial"; // แก้ไขสตริงหลายครั้ง (เช่น ต่อข้อความหรือลบบางส่วน) | D17: 1 | E17: 1 | F17: 1 | G17: 0 | H17: 0 | I17: 0 | J17: 1 | K17: 1 | L17: 1 | M17: 1 | N17: 1 | O17: 1 | P17: 1 | Q17: 0 | R17: 0 | S17: 0 | T17: 0 | U17: 1 | V17: 0 | W17: 1 | X17: 1 | Y17: 0 | Z17: 0 | AA17: 1 | AB17: 1 | AC17: 0 | AD17: 1 | AE17: 0 | AF17: 1 | AG17: 0 | AH17: 0 | AI17: 1 | AJ17: 0 | AL17: 1 | AM17: 0 | AN17: 1 | AO17: 0 | AP17: 1 | AQ17: 1 | AR17: 0 | AS17: 0 | AT17: 1 | AU17: 0 | AV17: 0 | AW17: 0 | AX17: 1
... A64: =A63+1 -> 60 | B64: =ข้อสอบ!B62 -> Process Area ใดใน CMMI ที่เกี่ยวข้องกับการใช้ Usecase model? | D64: 1 | E64: 1 | F64: 1 | G64: 1 | H64: 1 | I64: 1 | J64: 1 | K64: 1 | L64: 1 | M64: 1 | N64: 1 | O64: 1 | P64: 1 | Q64: 1 | R64: 1 | S64: 0 | T64: 1 | U64: 0 | V64: 1 | W64: 1 | X64: 1 | Y64: 1 | Z64: 1 | AA64: 1 | AB64: 1 | AC64: 1 | AD64: 1 | AE64: 0 | AF64: 1 | AG64: 0 | AH64: 0 | AI64: 1 | AJ64: 1 | AL64: 1 | AM64: 0 | AN64: 1 | AO64: 0 | AP64: 1 | AQ64: 1 | AR64: 0 | AS64: 0 | AT64: 1 | AU64: 1 | AV64: 1 | AW64: 1 | AX64: 0
A65: รวม | D65: =SUM(D5:D64) -> 42 | E65: =SUM(E5:E64) -> 57 | F65: =SUM(F5:F64) -> 55 | G65: =SUM(G5:G64) -> 45 | H65: =SUM(H5:H64) -> 40 | I65: =SUM(I5:I64) -> 40 | J65: =SUM(J5:J64) -> 54 | K65: =SUM(K5:K64) -> 58 | ... AX65: =SUM(AX5:AX64) -> 22

Sheet กระดาษทด
A1: กระดาษทด
A2: อนุญาตให้เขียน ข้อความหรือคำนวณใดๆ ก็ได้ในแผ่นงานนี้ โดยไม่ใช้เป็นคำตอบ

Sheet TeacherNote
D2: Bloom Taxonomy | J2: หัวข้อตามหลักสูตร | R2: หัวข้อเพิ่มเติ
D3: 1.Remember | E3: 2.Understand | F3: 3.Apply | G3: 4. Analyze | H3: 5. Evaluate | I3: 6. Create | J3: 1 การพัฒนาระบบซอฟต์แวร์ | K3: 2 การระบุข้อกำหนดของซอฟต์แวร์ เครื่องมือช่วยในการพัฒนาซอฟต์แวร์ | L3: 3 การเขียนโปรแกรมลักษณะมีแม่แบบแผน | M3: 4 การทดสอบซอฟต์แวร์ | N3: 5 การประกันคุณภาพ | O3: 6 การกำหนดหมายเลขกำกับการพัฒนา | P3: 7 ระบบควบคุมเวอร์ชัน | Q3: 8 โครงงานการพัฒนาระบบซอฟต์แวร์ | R3: 9 การเขียนโปรแกรมภาษา C# | S3: 10 html/css | T3: computer ethic
A4: ข้อ | B4: คำถาม | C4: เฉลย | D4: =COUNTIF(D5:D64, TRUE) -> 4 | E4: =COUNTIF(E5:E64, TRUE) -> 19 | F4: =COUNTIF(F5:F64, TRUE) -> 13 | G4: =COUNTIF(G5:G64, TRUE) -> 16 | H4: =COUNTIF(H5:H64, TRUE) -> 7 | I4: =COUNTIF(I5:I64, TRUE) -> 0 | J4: =COUNTIF(J5:J64, TRUE) -> 10 | K4: =COUNTIF(K5:K64, TRUE) -> 16 | ... T4: =COUNTIF(T5:T64, TRUE) -> 6
A5: =ข้อสอบ!A3 -> 1 | B5: =ข้อสอบ!B3 -> ใน Visual Studio 2022 เมื่อต้องการสร้างโปรเจกต์ใหม่สำหรับแอปพลิเคชัน Windows Forms โดยใช้ภาษา C# ควรเลือก แม่แบบ (เทมเพลต) ใด? | C5: ค | D5: TRUE | E5: FALSE | F5: FALSE | G5: FALSE | H5: FALSE | I5: FALSE | J5: FALSE | K5: FALSE | L5: TRUE | M5: FALSE | N5: FALSE | O5: FALSE | P5: FALSE | Q5: FALSE | R5: FALSE | S5: FALSE | T5: FALSE
A6: =ข้อสอบ!A4 -> 2 | B6: =ข้อสอบ!B4 -> ใน Visual Studio 2022 การกดปุ่ม F5 ขณะพัฒนาแอปพลิเคชัน Windows Forms มีผลอย่างไร? | C6: ข | D6: FALSE | E6: TRUE | F6: FALSE | G6: FALSE | H6: FALSE | I6: FALSE | J6: FALSE | K6: FALSE | L6: FALSE | M6: FALSE | N6: FALSE | O6: FALSE | P6: FALSE | Q6: FALSE | R6: TRUE | S6: FALSE | T6: FALSE
A7: =ข้อสอบ!A5 -> 3 | B7: =ข้อสอบ!B5 -> ถ้าต้องการเพิ่ม Button Control ลงในฟอร์มใน Visual Studio 2022 ควรทำอย่างไร? | C7: ข | D7: FALSE | E7: TRUE | F7: FALSE | G7: FALSE | H7: FALSE | I7: FALSE | J7: FALSE | K7: FALSE | L7: FALSE | M7: FALSE | N7: FALSE | O7: FALSE | P7: FALSE | Q7: FALSE | R7: TRUE | S7: FALSE | T7: FALSE
A8: =ข้อสอบ!A6 -> 4 | B8: =ข้อสอบ!B6 -> หลังจากเพิ่ม TextBox ชื่อ txtName และ Button ชื่อ btnSubmit ในฟอร์ม นักพัฒนาต้องการให้เมื่อคลิกปุ่ม btnSubmit โปรแกรมแสดงข้อความ "Hello, [ชื่อที่ป้อน]" ใน MessageBox ควรเขียนโค้ดอย่างไร? | C8: ก | D8: FALSE | E8: FALSE | F8: FALSE | G8: TRUE | H8: FALSE | I8: FALSE | J8: FALSE | K8: FALSE | L8: FALSE | M8: FALSE | N8: FALSE | O8: FALSE | P8: FALSE | Q8: FALSE | R8: TRUE | S8: FALSE | T8: FALSE
A9: =ข้อสอบ!A7 -> 5 | B9: =ข้อสอบ!B7 -> นักพัฒนาต้องการตรวจสอบว่าค่าในตัวแปร count ถูกอัปเดตอย่างถูกต้องขณะรันโปรแกรมในโหมด Debug วิธีใดเหมาะสมที่สุด? | C9: ข | D9: FALSE | E9: FALSE | F9: FALSE | G9: FALSE | H9: TRUE | I9: FALSE | J9: FALSE | K9: FALSE | L9: FALSE | M9: FALSE | N9: FALSE | O9: FALSE | P9: FALSE | Q9: FALSE | R9: TRUE | S9: FALSE | T9: FALSE
A10: =ข้อสอบ!A8 -> 6 | B10: =ข้อสอบ!B8 -> ในภาษา C# คีย์เวิร์ดใดใช้สำหรับประกาศตัวแปรที่เก็บค่าจำนวนเต็มแบบมีเครื่องหมายขนาด 32 บิต? | C10: ค | D10: FALSE | E10: TRUE | F10: FALSE | G10: FALSE | H10: FALSE | I10: FALSE | J10: FALSE | K10: FALSE | L10: FALSE | M10: FALSE | N10: FALSE | O10: FALSE | P10: FALSE | Q10: FALSE | R10: TRUE | S10: FALSE | T10: FALSE
A11: =ข้อสอบ!A9 -> 7 | B11: =ข้อสอบ!B9 -> ข้อใดคือการประกาศตัวแปรและกำหนดค่าเริ่มต้นที่ถูกต้องในภาษา C#? | C11: ค | D11: FALSE | E11: TRUE | F11: FALSE | G11: FALSE | H11: FALSE | I11: FALSE | J11: FALSE | K11: FALSE | L11: FALSE | M11: FALSE | N11: FALSE | O11: FALSE | P11: FALSE | Q11: FALSE | R11: TRUE | S11: FALSE | T11: FALSE
A12: =ข้อสอบ!A10 -> 8 | B12: =ข้อสอบ!B10 -> จากโค้ดต่อไปนี้ ผลลัพธ์ที่ได้คืออะไร? string message = "Hello"; message += " World"; Console.WriteLine(message.Length); | C12: ค | D12: FALSE | E12: FALSE | F12: FALSE | G12: TRUE | H12: FALSE | I12: FALSE | J12: FALSE | K12: FALSE | L12: FALSE | M12: FALSE | N12: FALSE | O12: FALSE | P12: FALSE | Q12: FALSE | R12: TRUE | S12: FALSE | T12: FALSE
A13: =ข้อสอบ!A11 -> 9 | B13: =ข้อสอบ!B11 -> ข้อใดคือวิธีที่ดีที่สุดในการตรวจสอบว่าสตริง input เป็นค่าว่างหรือไม่? | C13: ค | D13: FALSE | E13: FALSE | F13: FALSE | G13: FALSE | H13: TRUE | I13: FALSE | J13: FALSE | K13: FALSE | L13: FALSE | M13: FALSE | N13: FALSE | O13: FALSE | P13: FALSE | Q13: FALSE | R13: TRUE | S13: FALSE | T13: FALSE
A14: =ข้อสอบ!A12 -> 10 | B14: =ข้อสอบ!B12 -> จากโค้ดต่อไปนี้ ข้อใดคือผลลัพธ์และเหตุผลที่ถูกต้อง? int a = 10; int b = 3; double result = a / b; Console.WriteLine(result); | C14: ข | D14: FALSE | E14: FALSE | F14: FALSE | G14: FALSE | H14: TRUE | I14: FALSE | J14: FALSE | K14: FALSE | L14: FALSE | M14: FALSE | N14: FALSE | O14: FALSE | P14: FALSE | Q14: FALSE | R14: TRUE | S14: FALSE | T14: FALSE
A15: =ข้อสอบ!A13 -> 11 | B15: =ข้อสอบ!B13 -> ขั้นตอนใดใน SDLC ที่เกี่ยวข้องกับการวิเคราะห์ความต้องการของผู้ใช้และกำหนดขอบเขตของระบบ? | C15: ค | D15: FALSE | E15: TRUE | F15: FALSE | G15: FALSE | H15: FALSE | I15: FALSE | J15: TRUE | K15: FALSE | L15: FALSE | M15: FALSE | N15: FALSE | O15: FALSE | P15: FALSE | Q15: FALSE | R15: FALSE | S15: FALSE | T15: FALSE
A16: =ข้อสอบ!A14 -> 12 | B16: =ข้อสอบ!B14 -> หากองค์กรอยู่ใน CMMI Level 3 (Defined) ข้อใดสะท้อนลักษณะการทำงานได้ถูกต้องที่สุด? | C16: ก | D16: FALSE | E16: FALSE | F16: FALSE | G16: TRUE | H16: FALSE | I16: FALSE | J16: TRUE | K16: FALSE | L16: FALSE | M16: FALSE | N16: FALSE | O16: FALSE | P16: FALSE | Q16: FALSE | R16: FALSE | S16: FALSE | T16: FALSE
... A64: =ข้อสอบ!A62 -> 60 | B64: =ข้อสอบ!B62 -> Process Area ใดใน CMMI ที่เกี่ยวข้องกับการใช้ Usecase model? | C64: ก | D64: FALSE | E64: TRUE | F64: FALSE | G64: FALSE | H64: FALSE | I64: FALSE | J64: TRUE | K64: FALSE | L64: FALSE | M64: FALSE | N64: FALSE | O64: FALSE | P64: FALSE | Q64: FALSE | R64: FALSE | S64: FALSE | T64: FALSE
